<?xml version="1.0"?>

<model-hints>
	<model name="com.liferay.zain.practice.model.normal">
		<field name="sampleId" type="long" />
		<field name="groupId" type="long" />
		<field name="companyId" type="long" />
		<field name="userId" type="long" />
		<field name="userName" type="String" />
		<field name="createDate" type="Date" />
		<field name="modifiedDate" type="Date" />
		<field name="name" type="String" />
		<field name="catalog" type="String" />
		<field name="governorate" type="String" />
		<field name="areazone" type="String" />
	</model>
</model-hints>